byte_prefix_tree-0.3.2.dist-info/METADATA
byte_prefix_tree-0.3.2.dist-info/WHEEL
byte_prefix_tree-0.3.2.dist-info/license_files/LICENSE
byte_trie/base.py
byte_trie/__init__.py
byte_trie/version.py
byte_trie/__init__.pyi
byte_trie/_internal.abi3.so
byte_prefix_tree-0.3.2.dist-info/RECORD
