Metadata-Version: 2.1
Name: byte-prefix-tree
Version: 0.3.2
Classifier: Programming Language :: Rust
Classifier: Programming Language :: Python :: 3
Classifier: Topic :: Software Development :: Libraries
Classifier: Topic :: Text Processing
Classifier: Topic :: Utilities
License-File: LICENSE
Summary: Tries with byte sequences as keys for Python and Rust
Keywords: utilities,trie,byte,rust,python,patricia,art,radix
Author-email: Sebastian Walter <swalter@cs.uni-freiburg.de>
Requires-Python: >=3.10
Project-URL: Github, https://github.com/bastiscode/byte-trie
